{
  "drauvenName" : [ "<DrauvenFirstName> <DrauvenConstructedSurnamePrefix><DrauvenSurname>" ],
  "drauvenFirstName" : [ "_OR_", [ 2, "<PredefinedDrauvenFirstName>" ], [ 7, "<ConstructedDrauvenFirstName>" ], [ 1, "<SlavicName>" ] ],
  "predefinedDrauvenFirstName" : [ "Thuvayn", "Pyarc", "Vrsawl", "Zuvyac", "Colr", "Tranyen", "Mulsc", "Lwaug", "Fiorr", "Lauven", "Branok", "Merrek", "Litharel", "Zveth", "Xarro", "Vyxra", "Deek", "Thorall", "Styxis", "Tseth", "Ghirralosh", "Laurok", "Zveek", "Zvarok", "Tsyxra", "Litherrek", "Fiorall", "Stytharel", "Mexxis", "Hoshir", "Thogjuk", "Mophs", "Jipshish", "Masduk", "Kedag", "Idgril", "Uvzig", "Dygid", "Aofyrd", "Aukfethb", "Wfyrn", "Yfyrn", "Wyven", "Yvyrn" ],
  "constructedDrauvenFirstName" : [ "<DrauvenFirstNameBegin><drauvenFirstNameEnd>" ],
  "drauvenFirstNameBegin" : [ "lwa", "lau", "zve", "xar", "vyx", "styx", "ghirr", "tsyx", "mexx", "idgr", "thog", "thuv", "py", "vrs", "zu", "kyv", "ksu", "dra", "ts", "dee", "vra", "tsyr", "mul", "tran", "co", "du", "kyo", "kree", "cv", "ady", "boh", "dorb", "dar", "bor", "groz", "ylc", "kal", "uvz", "dyg", "auk", "yvy", "kve", "cas", "marz", "kras", "lju", "rost", "zbyh", "ves", "srbi", "zahv", "zby", "jaro", "zyz", "osor", "przby", "tych", "vla", "vyas", "zvez" ],
  "drauvenFirstNameEnd" : [ "ysl", "yn", "ayn", "arc", "rc", "rn", "orr", "rek", "ra", "reth", "veth", "xis", "eth", "rok", "xra", "rel", "duk", "yrn", "ish", "ysh", "wn", "osk", "ysk", "ssl", "xol", "awl", "vyac", "arr", "lr", "lrr", "yen", "sc", "st", "mpv", "yost", "esna", "ka", "jek", "rig", "rut", "myr", "oza", "zet", "ska", "vak", "wia", "cno", "acz", "ki", "cko" ],
  "slavicName" : [ "_OR_", [ 4, "<PredefinedSlavicName>" ], [ 1, "<DrauvenFirstNameBegin><drauvenFirstNameBegin><drauvenFirstNameEnd>" ] ],
  "predefinedSlavicName" : [ "Adis", "Admir", "Ajdin", "Baran", "Bialas", "Bladimiro", "Blagoje", "Blahoslav", "Boba", "Bohdan", "Boian", "Bojan", "Bojánek", "Bojek", "Bojík", "Bolek", "Boleslao", "Boleslav", "Boleslaw", "Boras", "Bore", "Borik", "Boris", "Borislav", "Borislaw", "Borja", "Borka", "Borut", "Boryusha", "Boza", "Bozidar", "Branik", "Branko", "Broda", "Brodny", "Bronislav", "Budimir", "Bylun", "Cas", "Casimear", "Casimir", "Casimyr", "Cich", "Cvetko", "Dalek", "Damear", "Danika", "Dark", "Darko", "Davor", "Desimir", "Dobrica", "Dobromir", "Dragan", "Drago", "Dragomir", "Dragoslav", "Dušan", "Duscha", "Estanislao", "Estanislaw", "Gniew", "Goran", "Izet", "Jarek", "Jarogniew", "Jaromir", "Jarousek", "Jezdimir", "Kąkol", "Kazek", "Kazik", "Kazimeras", "Kvetoslav", "Ladio", "Lao", "Lasota", "László", "Lech", "Ljuba", "Loman", "Łopata", "Lubomierz", "Maslaw", "Mecek", "Mecheslav", "Mecik", "Meckislavek", "Mieczyk", "Mieszko", "Mijo", "Miodrag", "Mladen", "Mscisclaw", "Mylan", "Nebojsa", "Nemanja", "Nenad", "Nepomuceno", "Novac", "Ognjen", "Osorio", "Plamen", "Pravaslav", "Preben", "Predrag", "Przbyslaw", "Radan", "Radek", "Radomir", "Rados", "Rosta", "Rostislav", "Rus", "Semir", "Sinisea", "Sladkea", "Slava", "Slavoljub", "Slawek", "Slobeslav", "Slobodan", "Srba", "Stando", "Stanko", "Svante", "Szydło", "Taman", "Techoslav", "Tihomir", "Uchacz", "Vaclav", "Vela", "Velimir", "Veloucek", "Vencel", "Venselau", "Vlad", "Vladan", "Vladi", "Vladimir", "Vladislav", "Vladja", "Vlatko", "Vojin", "Vojta", "Vuk", "Vukasin", "Vyashaslav", "Wlodzislaw", "Xexen", "Yaromir", "Yaropolk", "Yasen", "Žaba", "Zapototki", "Zbyna", "Zbynek", "Zbysek", "Zdravko", "Zelimir", "Zinion", "Zivon", "Zlatan", "Zlogonje", "Zoro", "Zorya", "Zvezdan", "Zvoncko", "Żyła", "Ajla", "Aleana", "Alyona", "Bilijona", "Biserka", "Brana", "Branka", "Brencis", "Capecca", "Chesna", "Bojana", "Cveta", "Dalenka", "Dalka", "Danja", "Darva", "Divna", "Bojka", "Dobra", "Dobromila", "Dobroslava", "Draga", "Dragica", "Duša", "Eudleana", "Eudlyna", "Gordana", "Grozdana", "Hourig", "Ilca", "Iskra", "Kalina", "Dejana", "Jarka", "Jagoda", "Jasna", "Jurissa", "Kalon", "Krasava", "Krasna", "Kveta", "Leposava", "Luba", "Lubov", "Marzhan", "Mil", "Miloslavia", "Miluša", "Miluska", "Mira", "Mren", "Nada", "Nadia", "Naida", "Nevenë", "Rada", "Radilla", "Radinka", "Radost", "Ratka", "Redmilla", "Roscislawa", "Rostuska", "Sanela", "Slavena", "Slavica", "Slobodanka", "Snežana", "Sobena", "Srbijanka", "Sveta", "Svetlana", "Svetochka", "Ural", "Vera", "Vesla", "Vesna", "Zagorka", "Zbyhneushka", "Zahvala", "Zdiska", "Zdisa", "Zitomeera", "Živa", "Zlata", "Zora", "Żywia", "Zvezdana", "Zyzlila", "Zyzila" ],
  "drauvenConstructedSurnamePrefix" : [ "_OR_", [ 2, "" ], [ 1, "" ] ],
  "drauvenSurname" : [ "_OR_", [ 2, "" ], [ 1, "" ] ],
  "drauvenHostileFaction" : [ "_OR_", [ 1, "Zagarac" ], [ 1, "Druvimos" ] ],
  "drauvenOutpostName" : [ "<DrauvenFirstNameBegin><drauvenFirstNameEnd> Outpost" ],
  "forbiddenWords" : [ "lochia", "eluna", "rivdin", "ryvdin", "rivdyn", "anivia", "vayne", "annelburn", "enma", "aynis", "enema", "darky", "moron", "bollock", "just", "anus", "mordor", "whitepride", "White Pride", "The White Pride", "whitepower", "fartol", "fartus", "farta", "fartana", "fartara", "farthai", "farthaia", "farthera", "fartia", "cocko", "farthan" ],
  "maleName" : [ "<MaleFirstName> <ConstructedSurnamePrefix><Surname>" ],
  "maleFirstName" : [ "_OR_", [ 3, "<PredefinedMaleFirstName>" ], [ 6, "<ConstructedMaleFirstName>" ] ],
  "constructedMaleFirstName" : [ "<FirstNameBegin><maleFirstNameEnd>" ],
  "femaleName" : [ "<FemaleFirstName> <ConstructedSurnamePrefix><Surname>" ],
  "femaleFirstName" : [ "_OR_", [ 3, "<PredefinedFemaleFirstName>" ], [ 6, "<ConstructedFemaleFirstName>" ] ],
  "constructedFemaleFirstName" : [ "<FirstNameBegin><femaleFirstNameEnd>" ],
  "constructedSurnamePrefix" : [ "_OR_", [ 1, "<SurnamePrefix>" ], [ 70, "" ] ],
  "surname" : [ "_OR_", [ 3, "<PredefinedSurname>" ], [ 5, "<ConstructedSurname>" ] ],
  "constructedSurname" : [ "<SurnameBegin><surnameEnd>" ],
  "predefinedMaleFirstName":["Aegnor","Aerandir","Aghan","Alatar","Aldor","Amandil","Amlach","Amras","Amrod","Anborn","Ancalagon","Andreth","Andróg","Angbor","Angrim","Angrod","Ar-Adûnakhôr","Ar-Gimilzôr","Ar-Pharazôn","Ar-Sakalthôr","Ar-Zimrathôn","Aragorn","Aratar","Aredhel","Arthad","Asgon","Aulë","Azaghâl","Balin","Barach","Baragund","Barahir","Baran","Bard","Barliman","Barrow","Beechbone","Beleg","Belegund","Bereg","Beren","Bifur","Bilbo","Bill","Bob","Bofur","Bombur","Borlach","Borlad","Boromir","Borthand","Brandir","Bregolas","Bregor","Bruno","Bëor","Bór","Caranthir","Carcharoth","Carl","Celeborn","Celebrimbor","Celegorm","Chieftain","Daeron","Damrod","Denethor","Dior","Durin","Dwalin","Déagol","Ecthelion","Eldarion","Elendil","Elendur","Elrohir","Elrond","Elros","Eluréd","Erellont","Erestor","Erkenbrand","Eru","Everard","Eärendur","Eöl","Falathar","Faramir","Fastred","Fili","Filibert","Finarfin","Finduilas","Finglas","Fingolfin","Fingon","Finrod","Finwë","Fladrif","Forlong","Fredegar","Frodo","Fuinur","Fëanor","Gaffer","Galdor","Gamgee","Gamil","Gamling","Gandalf","Gelmir","Ghân-buri-Ghân","Gil-galad","Gildor","Gimilkhâd","Gimli","Glaurung","Gleowine","Glirhuin","Glorfindel","Gloín","Glóin","Gollum","Gorbag","Gorlim","Gothmog","Grimbold","Grishnákh","Gríma","Guilin","Gundor","Guritz","Halbarad","Haldir","Haleth","Ham","Hamfast","Harry","Hirgon","Horn","Hugin","Hurin","Inglorien","Isildur","Khamûl","Kili","King","Legolas","Lobelia","Lord","Lothlórien","Lugdush","Lurtz","Maedhros","Mat","Mauhúr","Melkor","Meneldor","Merry","Morgoth","Murgash","Mûmakil","Nazgûl","Nestadion","Nilfaleth","Nob","Nori","Odo","Ori","Orophin","Otho","Pallando","Pippin","Quickbeam","Radagast","Rivendell","Rúmil","Sackville","Samwise","Sancho","Saruman","Sauron","Shadowfax","Shagrat","Sharku","Sméagol","Ted","Thingol","Thorin","Thranduil","Théoden","Théodred","Tom","Treebeard","Tuor","Twofoot","Túrin","Ufthak","Will","Éomund","Éothain","Aranwë","Bregalad","Brodda","Calmacil","Ciryon","Curufin","Círdan","Dori","Draugluin","Dairuin","Glóredhel","Éomer","Gwindor","Háma","Imrahil","Elladan","Eärendil","Landroval","Lotho","Madril","Snaga","Elrond","Elurín","Théoden", "Drogo","Tulkas","Telperion","Ulmo", "Sulimo", "Oromë","Aldaron", "Námo","Irmo"],
  "predefinedFemaleFirstName":["Aerin", "Amarië","Angelica","Annael","Aratan","Arien","Arwen","Belladonna","Diamond","Dorlas","Elwing","Emeldir","Eilinel","Elanor","Elatan","Elemmírë","Elenwë","Estë","Eärwen","Eönwë","Freda","Galadriel","Goldberry","Herefara","Idril","Iorlas","Irolas","Lady","Melian","Melilot","Míriel","Morwen","Robin","Rorimac","Rosie","Shelob","Silinde","Willow","Éowyn","Ungoliant","Nenya","Nessa","Varda","Lalaith","Yavanna","Elentari", "Kementári","Vána","Vairë","Uinen","Arien"],
  "predefinedSurname":["", "", "", "", "", "", "", "", "", "", "", "", "", "", "", "", "", "", "", "", "", "", "", "", "", "", "", "", "", "", "", "", "", "", "", "", "", "", "", "", "", "", "", "", "", "", "", "", "", "", "", "", "", "", "", "", "", "", "", "", "", "", "", "", "", "", "", "", "", "", "", "", "", "", "", "", "", "", "", "", "", "", "", "", "", "", "", "", "", "", "", "", "", "", "", "", "", "", "", "", "", "", "", "", "", "", "", "", "", "", "", "", "", "", "", "", "", "", "", "", "", "", "", "", "", "", "", "", "", "", "", "", "", "", "", "", "", "", "", "", "", "", "", "", "", "", "", "", "", "", "", "", "", "", "", "", "", "", "", "", "", "", "", "", "", "", "", "", "", "", "", "", "", "", "", "", "", "", "", "", "", "", "", "", "", "", "", "", "", "", "", "", "", "", "", "", "", "", "", "", "", "", "", "", "", "", "", "", "", "", "", "", "", "", "", "", "", "", "", "", "", "", "", "", "", "", "", "", "", "", "", "", "", "", "", "", "", "", "", "", "", "", "", "", "", "", "", "", "", "", "", "", "", "", "", "", "", "", "", "", "", "", "", "", "", "", "", "", "", "", "", "", "", "", "", "", "", "", "", "", "", "", "", "", "", "", "", "", "Tayvien", "Borien", "Andúnië","Angrod","Arnor","Baggins","Bane","Bolger","Bombadil","Bowman","Brandybuck","Butterbur","Cotton","Fountain","Galadriel","Gamgee","Heathertoes","Ilúvatar","Ladros","Maggot","Mahûd","Noakes","Númenor","Oakenshield","Proudfoot","Rumble","Sackville-Baggins","Sandyman","Smallburrow","Took","Turambar","Whitfoot","Wormtongue","Proudfoot","Zirak","Bracegirdle","Wight","Goatleaf","Old","Orc","Avarin","Ferny"],
  "firstNameBegin":["Ad","Ar", "Is", "Cel", "Mir", "Gal", "E", "A", "E", "Bor", "Far", "Cir", "El", "Maedh", "Mad", "Mag", "Cur", "Lal", "Lom", "Erein", "Gil", "Tur", "Fin", "Aredh", "Ared", "Mor", "Mir", "Or", "Tulc", "Elan", "Glin", "Fin", "Nol", "Nold", "Mel", "Meon", "Lind", "Nely", "Asy", "Ing", "Brand", "Theod", "Mar", "Orod", "Vor", "Hyar", "Har", "Maeg", "Olor", "Hal", "Mast", "Sedh", "Tyel", "Sar", "Rad", "Raur"],
  "maleFirstNameEnd":["or", "imbor", "omir", "amir", "ildur", "eborn", "ebrant", "oden", "than", "omer", "ol", "rond", "ros", "lor", "ufin", "finwe", "ion", "ion", "ion", "egorm", "galad", "gon", "agorn", "athorn", "athor", "ome", "as", "dan", "atar", "arfin", "olfin", "kor", "goth", "tumeon", "dur", "olas", "afar", "or", "reth", "onwe", "annas", "perian", "in", "arin", "ost", "perinquar", "rod", "uman", "agast", "os"],
  "femaleFirstNameEnd":["ynna","ynne","yvien", "wen", "wen", "wen", "gael", "iel", "adriel", "owyn", "aith", "we", "iel", "iel", "iel", "e", "isse", "ieth", "eth", "iria", "beth", "anel", "leth", "lith", "ava", "neth"],
  "surnamePrefix":["The  ", "Gil", "Ar-", "Tar-"],
  "surnameBegin":["Brandy","Bag","Gam","Proud","Brace","Bunce","Brown","Clay","Cot","Ro","Gon","Mag","Ar","Bolg","Bom","Bow","Oaken","Butter","Númen","Sack","Tur","Sandy","Barli","Heather","Whit","Blue","Grey","White","Fell","Fair","Tall","Grim","Merry","Worm","Goat","Small","Riven","Rhosc","Mirk","North","Horn","Tunnel","Mug","Barrow","Am","Mah"],
  "surnameEnd":["buck","wine","gins","strider","gee","foot","girdle","lock","hanger","ton","han","dor","got","nor","er","badil","man","shield","bur","hûd","ville-Baggins","ambar","man","toes","tongue","wight","leaf","burrow","dell","dale","obel","wood","grubb","ly","wort","wight","roth","took", "", "", "", "", "", "", "", "", "", "", "", "", "", "", "", "", "", "", "", "", "", "", "", "", "", "", "", "", "", "", "", "", "", "", "", "", "", "", "", "", "", "", "", "", "", "", "", "", "", "", "", "", "", "", "", "", "", "", "","", "", "", "", "", "", "", "", "", "", "","", "", "", "", "", "", "", "", "", "", "","", "", "", "", "", "", "", "", "", "", "","", "", "", "", "", "", "", "", "", "", "","", "", "", "", "", "", "", "", "", "", "","", "", "", "", "", "", "", "", "", "", "","", "", "", "", "", "", "", "", "", "", "", "", "", "", "", "","", "", "", "", "", "", "", "", "", "", "","", "", "", "", "", "", "", "", "", "", "","", "", "", "", "", "", "", "", "", "", "","", "", "", "", "", "", "", "", "", "", "", "", "", "", "", "", "", "", "", "", "", "", "", "", "", "", "", "", "", "", "", "", "", "", "", "", "","", "", "", "", "", "", "", "", "", "", "","", "", "", "", "", "", "", "", "", "", "",  "", "", "", "","", "", "", "", "", "", "", "", "", "", "","", "", "", "", "", "", "", "", "", "", "","", "", "", "", "", "", "", "", "", "", "","", "", "", "", "", "", "", "", "", "", "",  "", "", "", "","", "", "", "", "", "", "", "", "", "", "","", "", "", "", "", "", "", "", "", "", "","", "", "", "", "", "", "", "", "", "", "","", "", "", "", "", "", "", "", "", "", "",  "", "", "", "","", "", "", "", "", "", "", "", "", "", "","", "", "", "", "", "", "", "", "", "", "","", "", "", "", "", "", "", "", "", "", "","", "", "", "", "", "", "", "", "", "", "",  "", "", "", "","", "", "", "", "", "", "", "", "", "", "","", "", "", "", "", "", "", "", "", "", "","", "", "", "", "", "", "", "", "", "", "","", "", "", "", "", "", "", "", "", "", "",  "", "", "", "","", "", "", "", "", "", "", "", "", "", "","", "", "", "", "", "", "", "", "", "", "","", "", "", "", "", "", "", "", "", "", "","", "", "", "", "", "", "", "", "", "", "",  "", "", "", "","", "", "", "", "", "", "", "", "", "", "","", "", "", "", "", "", "", "", "", "", "","", "", "", "", "", "", "", "", "", "", "","", "", "", "", "", "", "", "", "", "", "",  "", "", "", "","", "", "", "", "", "", "", "", "", "", "","", "", "", "", "", "", "", "", "", "", "","", "", "", "", "", "", "", "", "", "", "","", "", "", "", "", "", "", "", "", "", "",  "", "", "", "","", "", "", "", "", "", "", "", "", "", "","", "", "", "", "", "", "", "", "", "", "","", "", "", "", "", "", "", "", "", "", "","", "", "", "", "", "", "", "", "", "", "",  "", "", "", "","", "", "", "", "", "", "", "", "", "", "","", "", "", "", "", "", "", "", "", "", "","", "", "", "", "", "", "", "", "", "", "","", "", "", "", "", "", "", "", "", "", "",  "", "", "", "","", "", "", "", "", "", "", "", "", "", "","", "", "", "", "", "", "", "", "", "", "","", "", "", "", "", "", "", "", "", "", "","", "", "", "", "", "", "", "", "", "", "",  "", "", "", "","", "", "", "", "", "", "", "", "", "", "","", "", "", "", "", "", "", "", "", "", "","", "", "", "", "", "", "", "", "", "", "","", "", "", "", "", "", "", "", "", "", "",  "", "", "", "","", "", "", "", "", "", "", "", "", "", "","", "", "", "", "", "", "", "", "", "", "","", "", "", "", "", "", "", "", "", "", "","", "", "", "", "", "", "", "", "", "", "",  "", "", "", "","", "", "", "", "", "", "", "", "", "", "","", "", "", "", "", "", "", "", "", "", "","", "", "", "", "", "", "", "", "", "", "","", "", "", "", "", "", "", "", "", "", "",  "", "", "", "","", "", "", "", "", "", "", "", "", "", "","", "", "", "", "", "", "", "", "", "", "","", "", "", "", "", "", "", "", "", "", "","", "", "", "", "", "", "", "", "", "", "",  "", "", "", "","", "", "", "", "", "", "", "", "", "", "","", "", "", "", "", "", "", "", "", "", "","", "", "", "", "", "", "", "", "", "", "","", "", "", "", "", "", "", "", "", "", "",  "", "", "", "","", "", "", "", "", "", "", "", "", "", "","", "", "", "", "", "", "", "", "", "", "","", "", "", "", "", "", "", "", "", "", "","", "", "", "", "", "", "", "", "", "", "",  "", "", "", "","", "", "", "", "", "", "", "", "", "", "","", "", "", "", "", "", "", "", "", "", "","", "", "", "", "", "", "", "", "", "", "","", "", "", "", "", "", "", "", "", "", "",  "", "", "", "","", "", "", "", "", "", "", "", "", "", "","", "", "", "", "", "", "", "", "", "", "","", "", "", "", "", "", "", "", "", "", "","", "", "", "", "", "", "", "", "", "", "",  "", "", "", "","", "", "", "", "", "", "", "", "", "", "","", "", "", "", "", "", "", "", "", "", "","", "", "", "", "", "", "", "", "", "", "","", "", "", "", "", "", "", "", "", "", "",  "", "", "", "","", "", "", "", "", "", "", "", "", "", "","", "", "", "", "", "", "", "", "", "", "","", "", "", "", "", "", "", "", "", "", "","", "", "", "", "", "", "", "", "", "", ""],
  "oceanTile" : [ "Almaren","Cair","Carrock","Elenna","Elvet-isle","Enchanted","Ened","Girdley","Himring","Isle","Luthany","Númenor","Tol","Tol-in-Gaurhoth","Tolfalas","Twilit","Íverin", "Andros","Balar","Brandir","Eressëa","Fuin","Galen","Island","Isles","Morwen","Seabirds","Sirion","Uinen","Withernon" ],
  "lakeTile" : [ "<LakeName> <LakeWord>", "Lake <LakeName>", "Sea of <lakeName>", "<lakeWord> of <lakeName>", "Loch <LakeName>" ],
  "lakeWord" : [ "Lake", "Reservoir", "Tear", "Widewater", "Sea", "Pond", "Waters" ],
  "lakeName" : [ "<lakePrefix> <lakeSuffix>" ],
  "lakePrefix": ["Aeluin","Afros","Ailin","Anduin","Arossiach","Baranduin","Bay","Brook","Bruinen","Bywater","Calenhir","Carnen","Celebrant","Celos","Ciril","Cobas","Crossings","Cuiviénen","Deeping-stream","Derrilyn","Dimrost","Drengist","Eithel","Enchanted","Entwade","Erui","Ethir","Ethraid","Falls","Firth","Five","Ford","Fords","Forest","Fôs'","Gilrain","Gladden","Glanduin","Gliding","Gollum's","Great","Greylin","Gruir","Gulf","Gwathló","Harnen","Helevorn","Henneth","Hoarwell","Híri","Icebay","Irtinsa","Kapalinda","Kelusindi","Kibil-nâla","Lake","Langwell","Lanthir","Lefnui","Lhûn","Limlight","Linaewen","Little","Long","Luvailin","Lórellin","Mering","Mirrormere","Mithe","Morgulduin","Morthond","Mouths","Nen","Nimrodel","Norbourn","North","Nunduinë","Nísinen","Old","Place","Pools","Poros","Rauros","Redwater","Rhimdath","Ringló","River","Rivers","Rivil","Rivil's","Sarn","Sea","Serni","Shadowmere","Shadowy","Shirebourn","Sirannon","Siril","Sirith","South","Stair","Stock-brook","Sîr","Tharbad","The","Thistle","Undeeps","Wells","Windle-reach","Withywindle"],
  "lakeSuffix": ["Almir","Anduin","Andúnië","Angren","Annûn","Athrad","Balar","Belfalas","Brithiach","Brook","Bruinen","Carrock","Eldamar","Eldanna","Engrin","Entwash","Erui","Esgalduin","Evendim","Falls","Ford","Forochel","Gebir","Glass","Gondor","Gulf","Haven","Helcar","Hithoel","Isen","Ivrin","Lake","Lalaith","Lamath","Lebennin","Lune","Mithrim","Nínui","Núrnen","Pool","Poros","Rhûn","Ringil","River","Running","Rómenna","Sirion","Spring","Stream","Undeep","Varda","Water","Well","in"],
  "coniferousForestTile" : [ "_OR_", [ 20, "<ForestTile>" ], "<Animal><coniferousTree> <ForestWord>", "<Descriptor><coniferousTree> <ForestWord>", "<Descriptor><coniferousTreePlural> <ForestWord>", "<Descriptor><animal> <ConiferousTreePlural>", "<ConstructedSurname> <ConiferousTreePlural>", "<SurnameBegin><animal> <ConiferousTreePlural>", "<SurnameBegin><coniferousTree> <ForestWord>" ],
  "coniferousTree" : [ "pine", "cedar", "fir", "spruce", "cypress" ],
  "coniferousTreePlural" : [ "pines", "cedars", "firs", "spruces" ],
  "deciduousForestTile" : [ "_OR_", [ 20, "<ForestTile>" ], "<Animal><deciduousTree> <ForestWord>", "<Descriptor><deciduousTree> <ForestWord>", "<Descriptor><deciduousTreePlural> <ForestWord>", "<Descriptor><animal> <DeciduousTreePlural>", "<ConstructedSurname> <DeciduousTreePlural>", "<SurnameBegin><animal> <DeciduousTreePlural>", "<SurnameBegin><deciduousTree> <ForestWord>" ],
  "deciduousTree" : [ "oak", "maple", "ash", "birch", "poplar", "beech", "alder", "aspen", "willow" ],
  "deciduousTreePlural" : [ "oaks", "maples", "ashes", "birches", "poplars", "aspens", "beeches", "willows" ],
  "forestTile" : [ "<Animal> <ForestWord>", "<Animal><forestSuffix>", "<Descriptor> <ForestWord>", "<GenericTile> <ForestWord>", "<SurnameBegin><forestSuffix>", "<SurnameBegin><animal> <ForestWord>", "<FirstNameBegin><forestSuffix>", "<FirstName><forestSuffix>", "<LastName> <ForestWord>" ],
  "forestWord" : [ "Adurant","Aear","Aearon","Aelin-uial","Aeluin","Aglarond","Aglon","Aldalómë","Ambaróna","Amon","Anach","Andram","Andrath","Androth","Anduin","Anfauglith","Angband","Anghabar","Angmar","Angren","Angrenost","Annon-in-Gelydh","Annúminas","Anórien","Arannor","Ard-galen","Argonath","Arnor","Aros","Arossiach","Arthedain","Arthórien","Ascar","Asgar","Avon","Balannor","Balar","Bar","Bar-en-Danwedh","Bar-en-Nibin-noeg","Bar-in-Mŷl","Barad","Barad-dûr","Baranduin","Belegaer","Belegost","Beleriand","Belfalas","Berennyn","Bindbole","Brethil","Brilthor","Brithombar","Brithon","Bruinen","Cabed","Cabed-en-Aras","Cair","Calenardhon","Calenhad","Carach","Caradhras","Caragdûr","Carchost","Cardolan","Carn","Carnen","Celduin","Celebdil","Celebrant","Celebros","Celon","Celos","Cerin","Chetwood","Ciril","Cirith","Crissaegrim","Côf","Cûl","Deldúwath","Dimbar","Dimholt","Dimrost","Dol","Dolmed","Dor","Dor-Cúarthol","Dor-Rodyn","Dor-en-Ernil","Dor-lómin","Doriath","Dorthonion","Drengist","Drúadan","Drúwaith","Drûn","Duilwen","Durthang","Dwimordene","Echad","Echoriad","Echoriath","Edhellond","Eglador","Eglarest","Eithel","Emyn","Emyn-nu-Fuin","Ened","Enedhwaith","Enedwaith","Ennor","Ephel","Erebor","Ered","Eregion","Eressai","Eriador","Erui","Eryn","Esgalduin","Esgaliant","Estolad","Ethir","Ethraid","Ethring","Everholt","Falas","Fangorn","Fanuidhol","Fen","Field","Firienholt","Forest","Forlindon","Forlond","Fornarthan","Fornost","Forochel","Forodwaith","Garthúrian","Gelion","Gevolon","Gilrain","Ginglith","Gladuial","Glanduin","Glanhír","Glithui","Gondolin","Gondor","Grey","Gwathir","Gwathló","Hadhodrond","Haerast","Halfirien","Harad","Haradwaith","Harathrad","Harlindon","Harlond","Harnen","Harondor","Haudh","Haudh-en-Arwen","Haudh-en-Ellas","Haudh-en-Elleth","Haudh-en-Ndengin","Lothlórien","Mirkwood","Nan","Neldoreth","Nimbrethil","Nivrim","Núath","Old","Taur-e-Ndaedelos","Taur-en-Faroth","Taur-im-Duinath","Taur-nu-Fuin","Tauremorna","Telain","Treegarth","Trollshaws","Wild","Woodland","Woods","Woody" ],
  "forestSuffix" : [ "Amarth","Amroth","Andros","Anduin","Angren","Anwar","Arnen","Belfalas","Brandir","Bîn","Caranthir","Cormallen","Daedeloth","Darthir","Duir","Dínen","Dîn","Dúath","Dûm","Eglain","Eithel","Elmoth","End","Engrin","Erain","Ereb","Erib","Ethir","Firn-i-Guinar","Forest","Fuir","Galen","Gorgor","Gorgoroth","Guldur","Gwanûr","Gwareth","Hen","Hollen","Iaur","Ivrin","Lanc","Lasgalen","Lhaw","Lithui","Luin","Lómin","Mithrin","Muil","Naeramarth","Neldoreth","Nimrais","Nimras","Ninniach","Obel","Oromë","Orthanc","Realm","Region","Rûdh","Sedryn","Sirion","Sûl","Tarlang","Thoronath","Tirith","Uial","Uilos","Ungol","Veleg","Vorn","Wethrin","Wood","in" ],
  "grasslandTile" : [ "<grasslandFirst> <GrasslandWord>", "<Descriptor><grasslandFirst> <GrasslandWord>", "<GenericTile>", "<GenericTile> <GrasslandWord>", "<Animal><grasslandWord>", "<Descriptor><grasslandWord>" ],
  "grasslandFirst": ["Anfauglith","Ard-galen","Blackroot","Bonfire","Bridgefields","Dagorlad","Deeping-coomb","Derndingle","Desert","Desolation","Dimrill","Dor-nu-Fauglith","Dwimorberg","East-mark","Eastemnet","Eastfarthing","Eastfold","Entwash","Estolad","Ettendales","Far","Farthings","Fenmark","Field","Firienfeld","Folde","Gap","Gladden","Grassland","Green","Greenfields","Harrowdale","Heath","Helm's","Himlad","Imloth","Ishmalog","Last","Lithlad","Lothlann","Marish","Morgul","Nan","Noirinan","Noman-lands","North","Northfarthing","Old","Overbourn","Parth","Party","Pastures","Pelennor","Plateau","Ringló","Rushock","Southfarthing","Stonewain","Talath","The","Tookland","Tumhalad","Tumladen","Udûn","Vale","Vales","Water-valley","West-march","West-mark","Westemnet","Westfarthing","Westfold","Westmarch","Withered","Woody"],
  "grasslandWord" : [ "Anduin","Bog","Celebrant","Cormallen","Country","Curunír","Dale","Deep","Desert","Dirnen","Downs","Dungortheb","End","Field","Fields","Galen","Glade","Gorgoroth","Heath","Hills","Lostladen","Marshes","Melui","Moors","Morannon","Narog","Rohan","Sirion","Sky-roof","Vale","Valley","Winyards","Wold","Yale","Yavanna","glen" ],
  "swampTile" : [ "<SwampWord> of <GenericTile>", "<FirstName>'s <SwampWord>", "<Descriptor><animal> <SwampWord>", "<Descriptor><swampSuffix>", "<FirstName>'s <Descriptor><swampSuffix>" ],
  "swampWord" : [ "moors", "bog", "marsh", "swamp", "wet", "wetland", "wetlands", "fen", "marshland", "mud", "moor", "mire", "bottoms" ],
  "swampSuffix" : [ "bog", "marsh", "swamp", "wet", "fen", "mud", "moor", "mire", "bottoms", "Neweglu","Nibin-noeg"],
  "genericTile" : [ "<genericTileFirst><regionSuffix>", "<genericTileLast><regionSuffix>", "<genericTileFirst> <genericTileLast>" ],
  "genericTileFirst":["Aelin-uial","Aeluin","Agar","Aglon","Alalminórë","Alley","Aman","Amon","Anach","Andram","Andrast","Androth","Anduin","Anfauglith","Angband","Anghabar","Angmar","Annon-in-Gelydh","Anórien","Araman","Arandor","Arch","Ard-galen","Arnor","Arossiach","Arsiriand","Arthórien","Arvernien","Atyamar","Balar","Bar","Barad","Barrow-downs","Bay","Belegost","Beleriand","Belfalas","Belmarie","Bladorinand","Blue","Bree-land","Brethil","Bridge","Bridgefields","Brithombar","Brodda's","Broseliand","Brown","Cabed-en-Aras","Calacirian","Calenardhon","Calenhir","Cape","Caragdûr","Celebros","Cirith","Coldfells","Crissaegrim","Cristhorn","Cuiviénen","Cú","Dagorlad","Dead","Deldúwath","Desolation","Dimbar","Dimrost","Dolmed","Dor","Dor-Cúarthol","Dor-Daideloth","Dor-en-Ernil","Dor-lómin","Dor-nu-Fauglith","Doriath","Dorthonion","Dorwinion","Drengist","Dry","Drúwaith","Drûn","Dunland","Durthang","Dwarf-road","East","Eastern","Echoriad","Egladil","Eglarest","Eithel","Emyn","Enedwaith","Ered","Eregion","Eriador","Estolad","Ettendales","Ettenmoors","Evadrien","Evereven","Falas","Fall","Falls","Fangair","Fangros","Fantasie","Far","Fen","Fens","Fingolfin's","Foen","Forannest","Forest","Forlindon","Forochel","Forostar","Fountains","Gar","Gates","Geleriand","Gelion","Gelion-Ascar","GenericSite","Girdle","Glingal","Golodhinand","Gondolin","Gondor","Gondothrimbar","Great","Greenfields","Halls","Harad","Harlindon","Helcaraxë","Helevorn","Hildórien","Hill","Himlad","Himring","Hithlum","House","Hírilorn","Hísilómë","Iant","Icebay","Idril's","Iron","Isle","Ithilien","Khand","Kortirion","Ladros","Lake","Lamedon","Lammoth","Land","Lanthir","Lassiriand","Lebennin","Leithien","Lesser","Linaewen","Lindon","Lisgardh","Lone-lands","Losgar","Lossarnach","Lothlann","Luthany","Maglor's","March","Marshes","Menegroth","Methed-en-glad","Minas","Mindeb","Minhiriath","Mirkwood","Mithrim","Moors","Mordor","Mountains","Mouths","Naith","Nan","Nan-tathren","Nargil","Nargothrond","Narog","Narrows","Nether","Nevrast","New","Nimbrethil","Nindalf","Nivrim","Nogrod","Noldórinan","North","Northern","Northlands","Nurn","Núath","Obel","Oiomúrë","Old","Orfalch","Orod-na-Thôn","Ossiriand","Palisor","Pass","Pine","Pine-mountain","Pinnath","Place","Plateau","Pools","Poros","Radhrim","Ramdal","Ras","Rathlóriel","Ravines","Rerir","Rhimdath","Rhovanion","Rivil","Rivil's","Road","Rohan","Sarn","Sarnas","Seven","Sindanórië","Sirion","South","Square","Swanfleet","Talath","Taras","Taras-ness","Tarnost","Tathrobel","Taur-en-Faroth","Taur-im-Duinath","Taur-na-Fuin","Taur-nu-Fuin","Tavrobel","Thangorodrim","Thargelion","Thellamie","Tol","Toll-ereb","Tower","Trollshaws","Tumhalad","Tumladen","Udul","Umbar","Utumno","Vale","Verna","Vinyamar","Way","West","Westlands","Withered"],
  "genericTileLast":["Aglon","Ainion","Arches","Athrad","Balar","Beleriand","Belthil","Bight","Cairn","Caranthir","Chimneys","Daedeloth","Darkness","Darthir","Dirnen","Dragon","Dungortheb","Dínen","Echor","Eglain","Eilch","Elmoth","Ereb","Eriador","Erib","Esgalduin","Ethir","Fingolfin","Firn-i-Guinar","Forest","Forochel","Galen","Gap","Gelin","Gondolin","Gondor","Gorgoroth","Gwareth","Halad","Harad","Heath","Iaur","Inwë","Ithilien","Ivrin","King","Lamath","Lands","Lómin","Lórien","Maedhros","Mandos","Market","Marshes","Melian","Mewrim","Mithrim","Mountains","Nargothrond","Neldoreth","Nevrast","Neweglu","Nibin-noeg","Nimras","Nínui","Obel","Palace","Pass","Plains","Pomps","Ransom","Region","Rhúnen","River","Road","Roses","Rûdh","Serech","Sirion","Slain","South","Stockade","Summer","Sun","Taeglin","Tavrobel","Thoronath","Tirith","Waste","Waters","Well","Wethrin","hall","lands","way"],
  "regionSuffix" : [ "land", "lend", "lund", "len", "ton", "tana", "ia", "usa", "onia", "ania", "usia", "ana", "ama", "ona", "ada", "ica", "ens", "or", "ay", "oth" ],
  "hillTile" : [ "<HillWord> of <GenericTile>", "<FirstName>'s <HillWord>", "<Descriptor><animal> <HillWord>", "<Descriptor><hillSuffix>", "<Animal><hillSuffix>", "<FirstName>'s <Descriptor><hillSuffix>", "<SurnameBegin><hillSuffix>" ],
  "hillSuffix" : ["Amroth","Anduin","Arnen","Baran","Bight","Celebrant","Country","Down","Downs","Dragon","Eglain","Ereb","Erech","Ethir","Evendim","Fields","Ford","Forest","Galadhon","Gate","Guard","Guldur","Gwareth","Hall","Halls","Heath","Hen","Hill","Hills","House","Lake","Lanc","Lands","Lhaw","Lórien","Marshes","Mirkwood","Morannon","Mountain","Mountains","Muil","Obel","Realm","Rhûn","Ridge","River","Road","Running","Rûdh","Scary","Slain","Thráin","Thrór","Undeep","Wild","raft-elves","sight"],
  "hillWord" : [ "Amon","Andram","Astulat","Atyamar","Barrow-downs","Beorn's","Bree-hill","Brown","Buck","Caras","Carnen","Carrock","Celebrant","Cerin","Dagorlad","Dale","Dead","Death","Desolation","Dol","Dorthonion","Dorwinion","Dáin's","East","Eastemnet","Egladil","Eilenaer","Elf-path","Elvenking's","Emyn","Enchanted","Erech","Ezellohar","Far","Field","Forest","Framsburg","Gladden","Great","Green","Grey","Greylin","Hill","Hills","Himring","Hobbiton","Hollin","Huts","Iron","Kibil-nâla","Kôr","Lake-town","Langwell","Limlight","Lonely","Long","Lothlórien","Mirkwood","Mountains","Narrows","Nimrodel","Noman-lands","North","Old","Oromet","Ramdal","Ravenhill","Redwater","Rhimdath","Rhosgobel","Rhovanion","River","Scary","Sea","Slag-hills","South","Tarnost","Taur-e-Ndaedelos","Taur-en-Faroth","The","Tower","Trollshaws","Túna","Undeeps","Vales","Weather","Weathertop","White","Withered","Woodland","hill" ],
  "mountainTile" : [ "<MountainWord> of <GenericTile>", "<FirstName>'s <MountainWord>", "<Descriptor><animal> <MountainWord>", "<Descriptor><mountainSuffix>", "<Animal><mountainSuffix>", "<FirstName>'s <Descriptor><mountainSuffix>", "<SurnameBegin><mountainSuffix>" ],
  "mountainSuffix" : ["Bîn","Darthir","Doom","Echor","Gram","Moria","Morthil","Mountain","Rohan","Taeglin","Tarlang","Uilos","Veleg" ],
  "mountainWord" : ["Amon","Antaro","Cabed-en-Aras","Caradhras","Caragdûr","Celebdil","Cûl","Dol","Dolmed","East","Ettenmoors","Fanuidhol","Foen","Gundabad","Hyarmentir","Kalormë","Lonely","Meneltarma","Methedras","Morgai","Mount","Mountain","Mountains","Orfalch","Orod-na-Thôn","Pine-mountain","Ras","Ravines","Rerir","Sorontil","Taniquetil","Taras","Thangorodrim","Zirak" ],
  "townName" : [ "_OR_", [ 15, "<townFirst> <townLast>" ], [ 5, "<townFirst>" ], [ 5, "<FounderFormula>" ], [ 5, "<NaturalFormula>" ], [ 1, "<NumericFormula>" ] ],
  "townFirst":["Aldburg","Amon","Angband","Annúminas","Archet","Armenelos","Avallonë","Barad-dûr","Bree","Brithombar","Budgeford","Bywater","Calembel","Caras","Carn","Cities","Harbours","Court","Dale","Deephallow","Dol","Dwaling","Edhellond","Edoras","Eglarest","Elvenking's","Ephel","Ethring","Forlond","Formenos","Fornost","Framsburg","Frogmorton","Front","Gamwich","Gar","Goblin","Gondolin","Greenholm","Grey","Halls","Hardbottle","Harlond","Havens","Hobbiton","Khazad-dum","King's","Kortirion","Lake","Lake-town","Linhir","Little","Lond","Lonely","Long","Longbottom","Menegroth","Michel","Minas","Mithlond","Nargothrond","Needlehole","Nobottle","Oatbarton","Osgiliath","Ost-in-Edhil","Overhill","Pelargir","Pincup","Rivendell","Rushey","Scary","Square","Stock","Tavrobel","Tharbad","Tighfield","Tirion","Tuckborough","Umbar","Underharrow","Undertowers","Upbourn","Utumno","Valmar","Vinyamar","Waymeet","Whitfurrows","Whitwell","Willowbottom","Woodhall"],
  "townLast":["Ainion","Amroth","Brandir","Cleeve","Court","Daer","Delving","Dûm","Falas","Fountain","Galadhon","Gondor","Halls","Havens","Lanc","Morgul","Númenor","Palace","Sirion","Thranduil","Tirith","Town","ports"],
  "founderFormula" : [ "<Founder>ton", "<Founder>brad", "<Founder>sted", "<Founder>burn", "<Founder>stead", "<Founder>moor", "<Founder>bridge", "<Founder>sbury", "<Founder>held", "<Founder>hold", "<Founder>fold", "<Founder>ford", "<Founder>feld", "<Founder>born", "<Founder>stram", "<Founder>wick", "<Founder>burg", "<Founder>shire", "<Founder>sher", "<Founder>bran", "<Founder>land" ],
  "naturalFormula" : [ "<Place><place>", "<Animal><place>", "<Descriptor><place>", "<Descriptor><animal>", "<Place><animal>" ],
  "numericFormula" : [ "Two<place>s", "Three<place>s", "Four<place>s", "Five<place>s", "Six<place>s", "Seven<place>s", "Eight<place>s", "Nine<place>s" ],
  "founderPlace" : [ "<founder>'s <Place>", "<Place> of <Founder>" ],
  "founder" : [ "<firstName>" ],
  "outdoorSite" : [ "<Founder>'s <Place>", "<Place> of <Founder>", "<Founder>'s <Descriptor> <Place>", "<Descriptor> <Place>", "<Descriptor> <Animal> <Place>", "<Place> of the <Animal>", "<Place> of the <Descriptor> <Animal>" ],
  "outdoorSiteNoFounder" : [ "<Descriptor> <Place>", "<Descriptor> <Animal> <Place>", "<Place> of the <Animal>", "<Place> of the <Descriptor> <Animal>" ],
  "outdoorSiteNoTown" : [ "<Founder>'s <Place>", "<Place> of <Founder>", "<Founder>'s <Descriptor> <Place>", "<Descriptor> <Place>", "<Descriptor> <Animal> <Place>", "<Place> of the <Animal>", "<Place> of the <Descriptor> <Animal>" ],
  "descriptor" : [ "deep", "sweet", "tall", "low", "high", "ashen", "north", "south", "east", "west", "hidden", "humble", "proud", "spook", "great", "good", "calm", "bad", "full", "silver", "golden", "bone", "white", "green", "rocky", "song", "mossy", "mossen", "dark", "swift", "ruby", "red", "fine", "blue", "violet", "amber", "fae", "stormy", "long", "wet", "fel", "bright", "gray", "quaint", "gran", "grand", "rich", "wilder", "whisky", "fallow", "wester", "souther", "ester", "narth", "woden", "loden", "grey", "yallow", "timber", "snowy", "wooden", "woody", "tainted", "glad", "smiling", "weeping", "tender", "soft", "hard", "still", "ever", "even", "dawny", "liven", "flaxen", "blond", "dusty", "near", "wyrd", "weird", "shamble", "angen", "gald", "windy", "black", "feather", "grim", "rust", "gusty", "musty", "axen", "misty", "misten", "cold", "cald", "warm", "glam", "gleaming", "glint", "cool", "rainy", "hardy", "stout", "burly", "barren", "friendly", "rolling", "muddy", "copper", "turning", "steel", "steely", "iron", "wounded", "gwelder", "hobble", "pale", "bumble", "grizzle", "broad", "slender", "slim", "narrow", "wailing", "singing", "fresh", "free", "bitter", "middle", "small", "large", "shrouded", "drained", "dry", "lucky", "ivory", "quiet", "pepper", "silent", "ringing", "dim", "fog", "foggy", "double", "trim", "triple", "stony", "trusty", "dancing", "painted", "emerald", "mellow", "stone", "gravel", "pebble", "yellow", "rusty", "carven", "old", "elder", "young", "bloody", "cloudy", "winding", "broken", "riven", "dapple", "foamy", "running", "leaping", "sleeping", "blazing", "blessed", "burning", "brave", "bold", "brisk", "shy", "shady", "sandy", "stamping", "howling", "grassy", "drifty", "plowed", "flying", "scant", "spare", "lofty", "hooting", "standing", "speaking", "wooly", "silken", "lonesome", "lone", "lonely", "looping", "supple", "lithe", "spilling", "funny", "clear", "sheer", "light", "brown", "ebon", "climbing", "jade", "rhyme", "jumping", "hefty", "sunny", "starry", "winsome", "blithe", "bonnie", "straw", "wary", "watching" ],
  "place" : [ "water", "found", "farm", "stoop", "wheel", "tree", "grove", "vale", "vel", "dale", "dell", "vell", "den", "wallow", "warn", "valley", "mount", "kiss", "cradle", "sheaf", "cave", "spring", "meadow", "creek", "crik", "stream", "stram", "lake", "home", "shore", "oak", "pine", "green", "peak", "roost", "feld", "grave", "grotto", "grom", "stoor", "field", "fary", "bury", "break", "reach", "hand", "glade", "hill", "barrow", "spire", "wick", "ford", "bridge", "track", "mountain", "ridge", "wand", "gram", "roast", "copse", "clare", "wicke", "wyck", "wycke", "hame", "ham", "sham", "hove", "post", "pose", "glenn", "mont", "glen", "send", "born", "brune", "brun", "shire", "burrogh", "heap", "watch", "shield", "wall", "fold", "cairn", "ring", "wend", "bog", "marsh", "swam", "swamp", "quarry", "fen", "reign", "wood", "stand", "fall", "fell", "mood", "path", "bed", "dam", "bane", "quarn", "sand", "stair", "flume", "fountain", "falls", "well", "rock", "burn", "burg", "brad", "heath", "lieth", "lyth", "stone", "share", "berg", "knoll", "shar", "shyre", "dome", "dolme", "curse", "scar", "scarn", "slope", "founder", "bask", "hearth", "stead", "town", "weld", "wold", "village", "cliff", "bank", "mere", "mure", "muir", "moor", "moore", "ville", "rest", "dark", "dure", "lodge", "dern", "fang", "flank", "stump", "crest", "hedge", "hem", "haven", "garden", "leap", "wald", "wild", "where", "hovel", "cove", "port", "ledge", "span", "bredth", "gap", "cape", "cast", "delve", "chapel", "rise", "pool", "secret", "hide", "dream", "heights", "gorge", "basin", "boon", "pond", "bern", "berm", "cross", "crossing", "dare", "run", "walk", "wake", "wane", "fane", "darg", "hall", "keep", "kiln", "bower", "bough", "barn", "wade", "pass", "bluff", "guff", "bonnet", "heart", "harth", "herth", "dwell", "bide", "bode", "bend", "hunch", "hinge", "mine", "mill", "forge", "mell", "will", "mull", "glass", "arch", "arc", "landing", "claim", "snare", "plot", "lock", "fend", "hobble", "nobble", "doggle", "cobble", "stub", "sable", "stable", "sire", "dune", "hook", "manse", "haunt", "manor", "pyre", "peer", "fald", "fence", "gate", "law", "faire", "fast", "trench", "guard", "gard", "castle", "tooth", "loom", "grade", "wist", "grim", "spike", "seed", "bloom", "brood", "drink", "dine", "brig", "dawn", "lure", "lair", "lyres", "skirt", "fires", "trails", "stell", "mills", "halls", "hills", "rivers", "creeks", "pip", "craw", "crown", "pock", "crater", "furrow", "spun", "tavern", "fork", "twist", "nook", "catch", "nock", "crook", "crock", "way", "moth", "mouth", "hub", "spoke", "rod", "helm", "nail", "range", "spade", "spit", "fire", "woe", "mourn", "ken", "kin", "kins", "kens", "comb", "com", "call", "calling", "kell", "side", "vigil", "crag", "worn", "tom", "mawth", "scape", "knee", "fore", "for", "yarn", "strife", "nest", "scour", "cown", "warren", "peril", "roam", "trap", "point", "pointe", "barrens", "view", "plight", "blight", "cope", "corn", "horn", "door", "stride", "stoke", "stock", "toke", "bath", "breth", "settle", "set", "seek", "sorrow", "top", "bottom", "cot", "cottage", "burrow", "burgh", "glyph", "lawn", "trail", "elm", "ash", "spot", "circle", "link", "stop", "stool", "ton", "fort", "hom", "still", "vill", "toss", "chuck", "ware", "bare", "bore", "market", "mark", "marck", "creak", "crick", "haus" ],
  "animal" : [ "bear", "elk", "falcon", "kestrel", "plow", "merlin", "fisher", "wolf", "lion", "hog", "deer", "moss", "honey", "griffon", "moose", "lamb", "stag", "pony", "foster", "smith", "cooper", "miller", "rouster", "weaver", "rabbit", "eagle", "buck", "dragon", "serpen", "crow", "raven", "ox", "bull", "wraith", "gian", "mason", "cedar", "rowan", "star", "water", "wader", "clover", "fern", "storm", "wrath", "tough", "guard", "brewer", "flower", "rose", "ivy", "newt", "frog", "mare", "roan", "toad", "river", "knight", "night", "day", "colt", "vixen", "troll", "rain", "snow", "thrush", "king", "queen", "lord", "lady", "sorrow", "gloom", "elder", "battle", "autumn", "spring", "winter", "summer", "blood", "horn", "ghost", "bread", "nut", "fawn", "swan", "duck", "cob", "tanner", "scribble", "maiden", "shepherd", "gale", "hart", "heart", "lizard", "dove", "hero", "villain", "gull", "comet", "spider", "thunder", "clan", "leaf", "mould", "widow", "elm", "oak", "birch", "alder", "wizard", "witch", "wright", "hammer", "hawker", "grain", "god", "rogue", "rook", "thief", "heron", "cook", "morn", "master", "war", "plum", "sage", "mallow", "tallow", "heather", "mystic", "ash", "apple", "daisy", "poppy", "thorn", "briar", "thistle", "crane", "fairy", "pixie", "mud", "snake", "berry", "worm", "wyrm", "bard", "ram", "goat", "echo", "cow", "captain", "shearer", "hermit", "rascal", "dandy", "searcher", "herder", "boar", "bogger", "shovel", "demon", "angel", "blade", "spear", "lizerd", "dame", "crone", "hound", "badger", "finch", "hawk", "bindle", "goblin", "otter", "pig", "dweller", "grym", "curr", "swine", "fox", "skull", "mirror", "munk", "bottle", "candle", "sword", "pike", "twin", "root", "cherry", "bell", "drum", "ember", "broom", "brush", "gamble" ],
  "towerSite" : [ "_OR_", [ 1, "<FounderTower>" ], [ 0.6, "<TownTower>" ], [ 1, "<NaturalTower>" ] ],
  "founderTower" : [ "<Founder>'s <TowerWord>", "<Founder> <TowerWord>" ],
  "townTower" : [ "<Town> <TowerWord>", "<TileName> <TowerWord>", "<TowerWord> of <TileName>" ],
  "naturalTower" : [ "<Descriptor><animal> <TowerWord>", "<Descriptor><place> <TowerWord>", "<Animal><place> <TowerWord>" ],
  "towerWord" : [ "tower", "spire", "keep", "hold", "lookout", "outlook", "rest", "watch", "post", "vigil", "monument", "boast", "pillar", "finger", "splinter", "stone", "ambition", "folly", "beacon" ],
  "tombSite" : [ "<Founder>'s <TombWord>", "<TombWord> of <Founder>" ],
  "tombWord" : [ "tomb", "grave", "rest", "stone", "tree", "crypt", "barrow", "restingplace", "sleep", "bed", "hallow", "peace", "fall", "fell", "pyre", "monument", "memorial", "doom", "oblivion", "fate", "grim", "cairn" ],
  "cavernSite" : [ "_OR_", [ 1, "<FounderCave>" ], [ 0.5, "<TownCave>" ], [ 1, "<NaturalCave>" ] ],
  "founderCave" : [ "<Founder> <CaveWord>", "<Founder>'s <CaveWord>", "<CaveWord> of <Founder>" ],
  "townCave" : [ "<Town> <CaveWord>", "<Town>'s <CaveWord>", "<CaveWord> of <Town>" ],
  "naturalCave" : [ "<caveWord> <caveLastWord>", "<caveLastWord> <caveWord>" ],
  "caveWord" : [ "Anach","Andrath","Androth","Angband","Anghabar","Calacirya","Carach","Cavern","Caves","Cirith","Dimrill","Front","Glittering","Henneth","High","House","Menegroth","Morgul","Nargil","Nargothrond","North","Orc-holds","Orfalch","Pass","Paths","Shelob's","Tarlang's","Trolls'","Wellinghall" ],
  "caveLastWord": ["Aglon","Angren","Annûn","Cave","Caves","Dead","Dúath","Echor","Forgotten","Gorgor","Lair","Neck","Ninniach","Pass","Porch","Ransom","Sirion","Stair","Thoronath","Ungol"],
  "libraryWord" : [ "stack", "stacks", "library", "shelves", "archive", "index", "lorekeep", "books", "bookpile", "learnings", "records", "tomes" ],
  "librarySite" : [ "<Founder>'s <LibraryWord>", "<Descriptor><place> <LibraryWord>", "<Animal><place> <LibraryWord>", "<Descriptor><animal> <LibraryWord>", "<TileName> <LibraryWord>" ],
  "genericSite" : [ "<lotrSiteFirst> <lotrSiteLast>", "<lotrSiteFirst>", "<lotrSiteLast>"],
  "lotrSiteFirst": ["Aelin-uial","Aeluin","Agar","Aglon","Alalminórë","Alley","Aman","Amon","Anach","Andram","Andrast","Androth","Anduin","Anfauglith","Angband","Anghabar","Angmar","Annon-in-Gelydh","Anórien","Araman","Arandor","Arch","Ard-galen","Arnor","Arossiach","Arsiriand","Arthórien","Arvernien","Atyamar","Balar","Bar","Barad","Barrow-downs","Bay","Belegost","Beleriand","Belfalas","Belmarie","Bladorinand","Blue","Bree-land","Brethil","Bridge","Bridgefields","Brithombar","Brodda's","Broseliand","Brown","Cabed-en-Aras","Calacirian","Calenardhon","Calenhir","Cape","Caragdûr","Celebros","Cirith","Coldfells","Crissaegrim","Cristhorn","Cuiviénen","Cú","Dagorlad","Dead","Deldúwath","Desolation","Dimbar","Dimrost","Dolmed","Dor","Dor-Cúarthol","Dor-Daideloth","Dor-en-Ernil","Dor-lómin","Dor-nu-Fauglith","Doriath","Dorthonion","Dorwinion","Drengist","Dry","Drúwaith","Drûn","Dunland","Durthang","Dwarf-road","East","Eastern","Echoriad","Egladil","Eglarest","Eithel","Emyn","Enedwaith","Ered","Eregion","Eriador","Estolad","Ettendales","Ettenmoors","Evadrien","Evereven","Falas","Fall","Falls","Fangair","Fangros","Fantasie","Far","Fen","Fens","Fingolfin's","Foen","Forannest","Forest","Forlindon","Forochel","Forostar","Fountains","Gar","Gates","Geleriand","Gelion","Gelion-Ascar","Girdle","Glingal","Golodhinand","Gondolin","Gondor","Gondothrimbar","Great","Greenfields","Halls","Harad","Harlindon","Helcaraxë","Helevorn","Hildórien","Hill","Himlad","Himring","Hithlum","House","Hírilorn","Hísilómë","Iant","Icebay","Idril's","Iron","Isle","Ithilien","Khand","Kortirion","Ladros","Lake","Lamedon","Lammoth","Land","Lanthir","Lassiriand","Lebennin","Leithien","Lesser","Linaewen","Lindon","Lisgardh","Lone-lands","Losgar","Lossarnach","Lothlann","Luthany","Maglor's","March","Marshes","Menegroth","Methed-en-glad","Minas","Mindeb","Minhiriath","Mirkwood","Mithrim","Moors","Mordor","Mountains","Mouths","Naith","Nan","Nan-tathren","Nargil","Nargothrond","Narog","Narrows","Nether","Nevrast","New","Nimbrethil","Nindalf","Nivrim","Nogrod","Noldórinan","North","Northern","Northlands","Nurn","Núath","Obel","Oiomúrë","Old","Orfalch","Orod-na-Thôn","Ossiriand","Palisor","Pass","Pine","Pine-mountain","Pinnath","Place","Plateau","Pools","Poros","Radhrim","Ramdal","Ras","Rathlóriel","Ravines","Rerir","Rhimdath","Rhovanion","Rivil","Rivil's","Road","Rohan","Sarn","Sarnas","Seven","Sindanórië","Sirion","South","Square","Swanfleet","Talath","Taras","Taras-ness","Tarnost","Tathrobel","Taur-en-Faroth","Taur-im-Duinath","Taur-na-Fuin","Taur-nu-Fuin","Tavrobel","Thangorodrim","Thargelion","Thellamie","Tol","Toll-ereb","Tower","Trollshaws","Tumhalad","Tumladen","Udul","Umbar","Utumno","Vale","Verna","Vinyamar","Way","West","Westlands","Withered"],
  "lotrSiteLast": ["Aglon","Ainion","Arches","Athrad","Balar","Beleriand","Belthil","Bight","Cairn","Caranthir","Chimneys","Daedeloth","Darkness","Darthir","Dirnen","Dragon","Dungortheb","Dínen","Echor","Eglain","Eilch","Elmoth","Ereb","Eriador","Erib","Esgalduin","Ethir","Fingolfin","Firn-i-Guinar","Forest","Forochel","Galen","Gap","Gelin","Gondolin","Gondor","Gorgoroth","Gwareth","Halad","Harad","Heath","Iaur","Inwë","Ithilien","Ivrin","King","Lamath","Lands","Lómin","Lórien","Maedhros","Mandos","Market","Marshes","Melian","Mewrim","Mithrim","Mountains","Nargothrond","Neldoreth","Nevrast","Neweglu","Nibin-noeg","Nimras","Nínui","Obel","Palace","Pass","Plains","Pomps","Ransom","Region","Rhúnen","River","Road","Roses","Rûdh","Serech","Sirion","Slain","South","Stockade","Summer","Sun","Taeglin","Tavrobel","Thoronath","Tirith","Waste","Waters","Well","Wethrin","hall","lands","way"],
  "earthworksSite" : [ "Earthworks at <GenericSite>" ],
  "quarrySite" : [ "<GenericSite> Quarry" ],
  "huntersBlindSite" : [ "<GenericSite>" ],
  "outfitterSite" : [ "Outfitter at <GenericSite>" ],
  "thresherySite" : [ "<GenericSite> Threshery" ],
  "tannerySite" : [ "<GenericSite> Tannery" ],
  "mineSite" : [ "<GenericSite> Mine" ],
  "lumberyardSite" : [ "<GenericSite> Lumberyard" ],
  "weaverworksSite" : [ "<GenericSite> Weaverworks" ],
  "forestShrineSite" : [ "<GenericSite> Shrine" ],
  "hengeSite" : [ "<GenericSite> Henge" ],
  "primalAltarSite" : [ "Altar of <GenericSite>" ],
  "dreamloomSite" : [ "<GenericSite> Dreamloom" ],
  "laboratorySite" : [ "<GenericSite> <LaboratoryWord>" ],
  "laboratoryWord" : [ "","","","","Council","Moot" ],
  "distillerySite" : [ "<GenericSite> <DistilleryWord>" ],
  "distilleryWord" : [ "Tavern", "Pub","Inn"],
  "fontSite" : [ "<GenericSite> <FontWord>", "<FontWord> of <GenericSite>" ],
  "fontWord" : [ "font", "well", "drift", "breath", "door", "fount", "manse", "seal", "spring", "fuse", "dream", "fluster", "focus", "star", "rift", "converge", "vergence" ],
  "forgeSite" : [ "<GenericSite> <ForgeWord>" ],
  "forgeWord" : [ "forge", "foundry", "smelter", "smithy", "smithery" ],
  "windmillSite" : [ "<GenericSite> Windmill", "<GenericSite> Vanes", "<GenericSite> Air-Engine", "<GenericSite> Chimes", "<GenericSite> Windworks" ],
  "waterwheelSite" : [ "<GenericSite> Dam", "Andrast","Cape","Eryn","Haerast","Hanstovánen","North","Qerkaringa","Ras","Rôs","Straits","Balar","Cape","Mewrim","Vorn" ],
  "groveSite" : [ "<Animal> <GroveWord>", "<Descriptor><animal> <GroveWord>", "<Animal><place> <GroveWord>" ],
  "groveWord" : [ "copse", "grove", "stand", "thicket", "trunks", "saplings", "hedge", "oldengrowth", "ring", "ancients", "glade", "glen", "shade", "arches", "entmoot" ],
  "foeWord" : [ "bandit", "beast", "blood", "bone", "chain", "cloud", "day", "dragon", "fear", "frost", "ghost", "giant", "gloom", "gristle", "hope", "iron", "king", "kings", "lich", "life", "light", "phantom", "queen", "queens", "serpent", "shadow", "skull", "sky", "smoke", "soul", "spell", "spider", "spine", "spirit", "steel", "stone", "terror", "time", "titan", "vile", "winter", "witch", "woe", "world", "wrath", "wraith", "wyrm" ],
  "crushableFoe" : [ "bandit", "barrow", "beast", "bond", "bone", "boulder", "beam", "beetle", "brain", "castle", "chain", "crown", "door", "dragon", "fear", "femur", "frost", "giant", "gloom", "goblin", "head", "gristle", "hall", "helm", "hill", "hope", "iron", "keep", "king", "kings", "lich", "life", "light", "mail", "moon", "mountain", "nail", "queen", "queens", "planet", "rib", "ring", "serpent", "shadow", "shield", "skull", "sky", "spell", "spider", "spine", "star", "stone", "table", "titan", "toe", "tomb", "tower", "town", "wall", "witch", "woe", "world", "wyrm" ],
  "woodType" : [ "-ash", "bark", "beech", "cedar", "cherry", "-elm", "-oak", "pine", "root", "rowan", "thorn", "tree", "willow", "wood", "yew" ],
  "wood1st" : [ "alder", "ashen", "aspen", "beech", "cedar", "cherry", "elm", "oaken", "pine", "root", "rowan", "thorn", "willow", "yew" ],
  "magicType" : [ "arcane", "astral", "astrological", "calling", "cosmic", "conjuring", "divining", "dreamsculpting", "dubious", "evoluthic", "enchanting", "encircling", "geomythic", "guarding", "guiding", "illuminating", "illusorific", "imbullient", "imperious", "infinity", "lithomantic", "mathworking", "mirror", "mistspilling", "mystical", "naturalist", "necrotic", "raincalling", "ruinous", "separating", "simulacrous", "siphoning", "sorcerous", "spellspeaking", "summoning", "sundering", "thaumaturgic", "verific", "weatherweaving" ],
  "magicEnding" : [ "astrology", "calling", "cosmologies", "conjuring", "divining", "dreamsculpting", "dubiosity", "evolution", "enchanting", "encircling", "geos", "guarding", "guiding", "illuminating", "illusion", "imbuement", "imposition", "lith", "mathworking", "mirrors", "mists", "mysticism", "naturalism", "necrotism", "rains", "ruin", "separating", "simulacrae", "siphoning", "sorcery", "speaking", "summoning", "sundering", "thaumaturgy", "veracity", "weatherweaving" ],
  "rapierWord" : [ "beam", "blade", "blossom", "brand", "breath", "dance", "dancer", "edge", "feather", "flare", "flash", "flayer", "foil", "line", "saber", "scribe", "shine", "slash", "sliver", "song", "spark", "splinter", "sword", "thorn", "tooth", "weaver" ],
  "rapierVirtue" : [ "black", "bleak", "bright", "cinder", "crimson", "dark", "dusk", "eagle", "ebon", "ember", "emerald", "falcon", "flame", "flicker", "fox", "golden", "grave", "gray", "green", "grim", "hawk", "ice", "lithe", "moon", "night", "quick", "raven", "red", "shade", "slender", "slim", "star", "storm", "sun", "sure", "swift", "thin", "thistle", "thunder", "violet", "viper", "water", "wind" ],
  "rapierBane" : [ "bane", "bite", "chiller", "dire", "fall", "lash", "needle", "pierce", "pin", "rake", "shock", "song", "scratch", "slash", "sting", "stitch", "tail", "thirst", "thrust", "thorn" ],
  "rapierName" : [ "<FoeWord><rapierBane>", "<RapierVirtue><rapierWord>", "<RapierVirtue><rapierWord> of <GenericSite>", "The <RapierVirtue> <RapierWord>", "<RapierVirtue><foeWord>'s <RapierBane>" ],
  "sword1handWord" : [ "beam", "bell", "blade", "brand", "call", "claim", "claw", "cry", "edge", "flame", "flare", "flash", "mark", "shard", "shine", "slash", "song", "strike", "sword", "thorn", "tooth", "wail" ],
  "sword1handVirtue" : [ "battle", "black", "bleak", "briar", "bright", "cinder", "crimson", "dark", "dusk", "ebon", "ember", "emerald", "fox", "glory", "golden", "grave", "gray", "green", "grim", "hawk", "ice", "lang", "lion", "long", "moon", "morning", "mountain", "night", "noon", "rain", "raven", "red", "shade", "silver", "star", "storm", "strong", "summer", "sun", "sure", "thunder", "true", "violet", "water", "wild", "wind", "wolf", "wolfen" ],
  "sword1handBane" : [ "bane", "bite", "breaker", "chiller", "clash", "cleave", "cutter", "dire", "doom", "dread", "end", "fall", "fate", "omen", "price", "ripper", "sever", "shear", "slash", "song", "strike", "swipe", "thirst", "thrust", "thorn", "toll", "wail" ],
  "sword1handName" : [ "<FoeWord><sword1handBane>", "<Sword1handVirtue><sword1handWord>", "<Sword1handVirtue><sword1handWord> of <GenericSite>", "The <Sword1handVirtue> <Sword1handWord>", "<Sword1handVirtue><foeWord>'s <Sword1handBane>" ],
  "sword2handWord" : [ "bell", "blade", "brand", "call", "claim", "claw", "cry", "edge", "flame", "howl", "oath", "price", "rend", "shard", "slash", "song", "strike", "sword", "tooth", "tusk", "wail" ],
  "sword2handVirtue" : [ "battle", "bear", "black", "bleak", "cinder", "crimson", "dark", "deep", "dusk", "ebon", "ember", "emerald", "golden", "grave", "gray", "great", "green", "grim", "ice", "lang", "lion", "long", "moon", "mountain", "mourning", "noon", "night", "olden", "rain", "red", "shade", "shatter", "silver", "somber", "star", "storm", "strong", "summer", "sun", "sure", "thunder", "true", "water", "wild", "wilder", "wind" ],
  "sword2handBane" : [ "bane", "bite", "breaker", "chasm", "clash", "cleaver", "crusher", "dirge", "drinker", "fall", "fate", "flame", "howl", "killer", "masher", "rend", "ripper", "ruin", "seal", "sever", "shear", "slicer", "song", "splitter", "strike", "swipe", "thirst", "toll", "vengeance", "wail" ],
  "sword2handName" : [ "<FoeWord><sword2handBane>", "<Sword2handVirtue><sword2handWord>", "<Sword2handVirtue><sword2handWord> of <GenericSite>", "The <Sword2handVirtue> <Sword2handWord>", "<Sword2handVirtue><foeWord>'s <Sword2handBane>" ],
  "axe1handWord" : [ "axe", "bite", "break", "burn", "claim", "clash", "cleave", "crash", "edge", "fall", "fell", "gash", "glare", "gnaw", "gore", "gouge", "grim", "hew", "howl", "jaw", "oath", "quake", "shard", "song", "tusk", "wail", "wave" ],
  "axe1handVirtue" : [ "battle", "bear", "black", "bleak", "bracken", "bull", "cinder", "crimson", "dark", "deep", "dusk", "ebon", "ember", "fire", "golden", "grave", "gray", "great", "green", "ice", "moon", "mountain", "mourning", "noon", "night", "old", "ox", "rage", "rain", "red", "shade", "shatter", "silver", "storm", "strong", "sun", "sure", "thunder", "true", "wild", "wilder" ],
  "axe1handBane" : [ "bane", "bite", "breaker", "chase", "chopper", "clash", "cleave", "cleaver", "dirge", "drinker", "eater", "eye", "fall", "fate", "fell", "feller", "gasher", "gnaw", "gore", "hack", "hacker", "hewer", "hew", "howl", "jaw", "killer", "masher", "ripper", "ruin", "sever", "shear", "song", "splitter", "tear", "thirst", "toll", "trapper", "tusk", "vengeance", "wail" ],
  "axe1handName" : [ "<FoeWord><axe1handBane>", "<Axe1handVirtue><axe1handWord>", "<Axe1handVirtue><axe1handWord> of <GenericSite>", "The <Axe1handVirtue> <Axe1handWord>", "<Axe1handVirtue><foeWord>'s <Axe1handBane>" ],
  "axe2handWord" : [ "axe", "bite", "break", "burn", "claim", "clash", "cleave", "crash", "edge", "fall", "fell", "gash", "glare", "gnaw", "gore", "gouge", "grim", "hew", "howl", "jaw", "oath", "quake", "shard", "song", "tide", "tusk", "wail", "wave" ],
  "axe2handVirtue" : [ "battle", "bear", "black", "bleak", "bracken", "bull", "cinder", "crimson", "dark", "deep", "dusk", "ebon", "ember", "fire", "golden", "grave", "gray", "great", "green", "ice", "moon", "mountain", "mourning", "noon", "night", "old", "ox", "rage", "rain", "red", "shade", "shatter", "silver", "storm", "sun", "sure", "thunder", "true", "wild", "wilder" ],
  "axe2handBane" : [ "bane", "bite", "breaker", "chase", "chopper", "clash", "cleave", "cleaver", "dirge", "drinker", "eater", "fall", "fate", "fell", "feller", "gasher", "gnaw", "gore", "hack", "hacker", "hewer", "hew", "howl", "jaw", "killer", "masher", "ripper", "ruin", "sever", "shear", "song", "splitter", "tear", "thirst", "toll", "trapper", "tusk", "vengeance", "wail" ],
  "axe2handName" : [ "<FoeWord><axe2handBane>", "<Axe2handVirtue><axe2handWord>", "<Axe2handVirtue><axe2handWord> of <GenericSite>", "The <Axe2handVirtue> <Axe2handWord>", "<Axe2handVirtue><foeWord>'s <Axe2handBane>" ],
  "mace1handWord" : [ "bash", "break", "clap", "clash", "club", "crash", "crush", "fist", "flail", "force", "mace", "moon", "shatterer", "shiver", "smash", "star", "stone", "sun", "wallop", "wrath" ],
  "mace1handVirtue" : [ "black", "bleak", "crimson", "dark", "deep", "dusk", "ebon", "ember", "golden", "gray", "great", "green", "ice", "mountain", "night", "olden", "quake", "rage", "red", "shock", "silver", "storm", "stout", "sure", "thunder", "true", "wild" ],
  "mace1handBane" : [ "basher", "breaker", "clash", "crusher", "fate", "masher", "mauler", "mulcher", "ruin", "smasher", "song", "thrasher", "thresher", "toll" ],
  "mace1handName" : [ "<Mace1handVirtue><mace1handWord>", "<Mace1handVirtue><mace1handWord> of <GenericSite>", "The <Mace1handVirtue> <Mace1handWord>", "<Mace1handVirtue><foeWord>'s <Mace1handBane>", "<CrushableFoe><mace1handBane>", "The <CrushableFoe> <Mace1handBane>" ],
  "mace2handWord" : [ "bash", "break", "clash", "crash", "crush", "fall", "fist", "force", "gavel", "hammer", "mallet", "maul", "shatterer", "shiver", "sledge", "smash", "wallop", "wrath" ],
  "mace2handVirtue" : [ "black", "bleak", "crimson", "dark", "deep", "dusk", "ebon", "ember", "golden", "grave", "gray", "great", "green", "ice", "iron", "mountain", "night", "olden", "quake", "rage", "red", "shock", "silver", "storm", "stout", "sure", "thunder", "true", "wild" ],
  "mace2handBane" : [ "basher", "breaker", "clash", "crusher", "fate", "masher", "mauler", "mulcher", "pounder", "ruin", "sludger", "smasher", "song", "thrasher", "thresher", "toll" ],
  "mace2handName" : [ "<Mace2handVirtue><mace2handWord>", "<Mace2handVirtue><mace2handWord> of <GenericSite>", "The <Mace2handVirtue> <Mace2handWord>", "<Mace2handVirtue><foeWord>'s <Mace2handBane>", "<CrushableFoe><mace2handBane>", "The <CrushableFoe> <Mace2handBane>" ],
  "spear1handWord" : [ "call", "beam", "claim", "fall", "glaive", "pierce", "rail", "reach", "root", "shock", "song", "spear", "spike", "spindle", "spine", "spoke", "stake", "sting", "stroke", "strike", "tail", "thorn", "tooth", "truth", "weaver" ],
  "spear1handVirtue" : [ "amber", "ash", "autumn", "black", "bleak", "bright", "cinder", "crimson", "crow", "dark", "dusk", "ebon", "ember", "falcon", "flame", "fox", "golden", "gray", "green", "grim", "hawk", "ice", "lion", "lithe", "lizard", "moon", "mountain", "night", "owl", "panther", "red", "shade", "snake", "star", "storm", "sun", "sure", "swift", "thistle", "thunder", "viper", "wave", "whisper", "wind", "wyvern" ],
  "spear1handBane" : [ "bane", "doom", "end", "fall", "fate", "fell", "glance", "grief", "gutter", "killer", "lance", "needle", "oath", "piercer", "pin", "quiet", "quill", "skewer", "spear", "spit", "stitch", "thirst", "thrust", "thorn" ],
  "spear1handName" : [ "<FoeWord><spear1handBane>", "<Spear1handVirtue><spear1handWord>", "<Spear1handVirtue><spear1handWord> of <GenericSite>", "The <Spear1handVirtue> <Spear1handWord>", "<Spear1handVirtue><foeWord>'s <Spear1handBane>" ],
  "spear2handWord" : [ "beam", "call", "claim", "fall", "glaive", "lance", "nail", "pierce", "pike", "rail", "reach", "root", "shock", "song", "spear", "spike", "spindle", "spine", "spoke", "stake", "sting", "stroke", "strike", "tail", "thorn", "tooth", "truth", "weaver" ],
  "spear2handVirtue" : [ "amber", "ash", "autumn", "black", "bleak", "bright", "cinder", "crimson", "crow", "dark", "dusk", "ebon", "ember", "falcon", "flame", "fox", "golden", "gray", "green", "grim", "hawk", "ice", "lion", "lithe", "lizard", "moon", "mountain", "night", "owl", "panther", "red", "shade", "snake", "star", "storm", "sun", "sure", "swift", "thistle", "thunder", "viper", "wave", "whisper", "wind", "wyvern" ],
  "spear2handBane" : [ "bane", "doom", "end", "fall", "fate", "fell", "glance", "grief", "gutter", "killer", "lance", "needle", "oath", "piercer", "pin", "quiet", "quill", "skewer", "spear", "spit", "stitch", "thirst", "thrust", "thorn" ],
  "spear2handName" : [ "<FoeWord><spear2handBane>", "<Spear2handVirtue><spear2handWord>", "<Spear2handVirtue><spear2handWord> of <GenericSite>", "The <Spear2handVirtue> <Spear2handWord>", "<Spear2handVirtue><foeWord>'s <Spear2handBane>" ],
  "daggerWord" : [ "blade", "bloom", "blossom", "dagger", "dirk", "edge", "file", "gale", "grim", "grief", "knife", "leaf", "lock", "orchid", "promise", "rose", "shard", "sigh", "slash", "thorn", "tooth", "truth" ],
  "daggerVirtue" : [ "ash", "autumn", "black", "bleak", "bright", "crimson", "crow", "dark", "dusk", "ebon", "ember", "ever", "falcon", "flame", "fox", "golden", "gray", "green", "hawk", "ice", "jade", "jagged", "lithe", "lizard", "moon", "red", "shade", "silent", "slender", "slim", "snake", "star", "storm", "sun", "sure", "swift", "thistle", "viper", "weeping", "whisper", "wind", "wing" ],
  "daggerBane" : [ "bane", "carver", "fall", "fate", "grief", "grim", "keeper", "lock", "mourn", "night", "oath", "secret", "sigh", "skinner", "stabber", "thorn", "trifle" ],
  "daggerName" : [ "<FoeWord><daggerBane>", "<DaggerVirtue><daggerWord>", "<DaggerVirtue><daggerWord> of <GenericSite>", "The <DaggerVirtue> <DaggerWord>", "<DaggerVirtue><foeWord>'s <DaggerBane>" ],
  "bowWord" : [ "arc", "bow", "curve", "howl", "pride", "quill", "seeker", "song", "striker", "weaver" ],
  "bowVirtue" : [ "autumn", "black", "blush", "bright", "crimson", "crow", "dark", "dusk", "ebon", "ember", "ever", "falcon", "fay", "flame", "fox", "golden", "gray", "green", "grim", "hawk", "heron", "hornet", "ice", "jade", "lithe", "moon", "myth", "night", "red", "rook", "shade", "silent", "slender", "slim", "snake", "star", "storm", "sun", "sure", "swift", "thistle", "viper", "whip", "whisper", "wind", "wing" ],
  "bowBane" : [ "arrow", "bane", "blight", "end", "fall", "fell", "hunter", "killer", "mark", "piercer", "strike", "thorn", "seeker", "taker", "weaver" ],
  "bowName" : [ "<FoeWord><bowBane>", "<BowVirtue><bowWord>", "<BowVirtue><bowWord> of <GenericSite>", "The <BowVirtue> <BowWord>", "<BowVirtue><woodType> <BowWord>", "<Wood1st><bowWord> of <GenericSite>", "<Wood1st><bowWord>" ],
  "crossbowWord" : [ "bow", "cross", "howl", "price", "seeker", "snap", "song", "striker", "thrower", "weaver" ],
  "crossbowVirtue" : [ "autumn", "black", "crimson", "crow", "dark", "dusk", "ebon", "ember", "ever", "falcon", "flame", "fox", "golden", "gray", "green", "grim", "hawk", "ice", "jade", "moon", "myth", "night", "red", "rook", "shade", "silent", "snake", "star", "storm", "sun", "sure", "swift", "thistle", "viper", "whisper", "wind", "wing", "wolf" ],
  "crossbowBane" : [ "bane", "blight", "bolt", "end", "fall", "fell", "hunter", "killer", "mark", "piercer", "strike", "thorn", "seeker", "taker", "weaver" ],
  "crossbowName" : [ "<FoeWord><crossbowBane>", "<CrossbowVirtue><crossbowWord>", "<CrossowVirtue><crossbowWord> of <GenericSite>", "The <CrossbowVirtue> <CrossbowWord>", "<CrossbowVirtue><woodType> <CrossbowWord>", "<Wood1st><crossbowWord> of <GenericSite>", "<Wood1st><crossbowWord>" ],
  "staffWord" : [ "bough", "branch", "cane", "crook", "crutch", "limb", "perch", "pillar", "rattle", "shaker", "staff", "ward" ],
  "staffVirtue" : [ "autumn", "black", "crow", "dark", "dusk", "ebon", "ember", "ever", "fay", "fire", "flame", "fox", "golden", "gray", "green", "grim", "hawk", "heron", "ice", "jade", "moon", "myth", "night", "owl", "red", "rook", "shade", "silent", "slender", "snake", "star", "storm", "summer", "sun", "sure", "thistle", "whisper", "wind", "wing" ],
  "staffBane" : [ "abolisher", "blaster", "croiler", "dirge", "doom", "dredge", "drinker", "ensorceller", "entangler", "unraveler", "wilter", "witherer" ],
  "staffName" : [ "<FoeWord> <StaffBane>", "<GenericSite>'s <StaffWord>", "<StaffVirtue><staffWord>", "<StaffVirtue><staffWord> of <GenericSite>", "<StaffVirtue><woodType> <StaffWord>", "The <StaffVirtue><foeWord> <StaffBane>", "<MagicType> <StaffVirtue><staffWord>", "<MagicType> <Wood1st><staffWord>", "<Wood1st><staffWord> of <MagicEnding>", "<MagicType> <StaffWord> of <GenericSite>", "<CrushableFoe> <StaffBane>", "<StaffBane> of the <CrushableFoe>", "<Wood1st><staffWord> of <GenericSite>" ],
  "wandWord" : [ "branch", "cane", "fletch", "flim", "flog", "perch", "rattle", "rod", "scepter", "shaker", "sprig", "strand", "switch", "twig", "wand", "ward", "whip", "wick" ],
  "wandVirtue" : [ "autumn", "black", "crow", "dark", "dusk", "ebon", "ember", "ever", "fay", "fire", "flame", "fox", "golden", "gray", "green", "grim", "hawk", "heron", "ice", "jade", "moon", "myth", "night", "owl", "red", "rook", "shade", "silent", "slender", "snake", "star", "storm", "summer", "sun", "sure", "thistle", "whisper", "wind", "wing" ],
  "wandBane" : [ "abolisher", "blaster", "croiler", "dirge", "doom", "dredge", "drinker", "ensorceller", "entangler", "unraveler", "wilter", "witherer" ],
  "wandName" : [ "<FoeWord> <WandBane>", "<GenericSite>'s <WandWord>", "<WandVirtue><wandWord>", "<WandVirtue><wandWord> of <GenericSite>", "<WandVirtue><woodType> <WandWord>", "The <WandVirtue><foeWord> <WandBane>", "<MagicType> <WandVirtue><wandWord>", "<MagicType> <Wood1st><wandWord>", "<Wood1st><wandWord> of <MagicEnding> ", "<MagicType> <WandWord> of <GenericSite>", "<CrushableFoe> <WandBane>", "<WandBane> of the <CrushableFoe>", "<Wood1st><wandWord> of <GenericSite>" ]
}
